rte_api/__init__.py
rte_api/balancing_energy/BalancingEnergy.py
rte_api/balancing_energy/__init__.py
rte_api/big_adjusted/BigAdjusted.py
rte_api/big_adjusted/__init__.py
rte_api/common/API.py
rte_api/common/RTE.py
rte_api/common/__init__.py
rte_api/common/headers/HTTP.py
rte_api/common/headers/__init__.py
rte_api/wholesale_market/WholesaleMarket.py
rte_api/wholesale_market/__init__.py
rte_python_api-0.0.3.dist-info/licenses/License.txt
rte_python_api-0.0.3.dist-info/METADATA
rte_python_api-0.0.3.dist-info/WHEEL
rte_python_api-0.0.3.dist-info/top_level.txt
rte_python_api-0.0.3.dist-info/RECORD
